yamlish.py
yamlish-0.18.1.dist-info/top_level.txt
yamlish-0.18.1.dist-info/METADATA
yamlish-0.18.1.dist-info/DESCRIPTION.rst
yamlish-0.18.1.dist-info/metadata.json
yamlish-0.18.1.dist-info/WHEEL
yamlish-0.18.1.dist-info/RECORD
